{
  "manifest_version": 3,
  "name": "Word Counter Plus",
  "version": "1.0.1",
  "description": "Analyze any text instantly - word count, character count, readability score, keyword extraction, and export options! Works 100% offline.",
  "permissions": [
    "contextMenus",
    "storage"
  ],
  "background": {
    "scripts": ["background.js"]
  },
  "action": {
    "default_popup": "popup/popup.html",
    "default_icon": {
      "16": "icons/icon16.png",
      "32": "icons/icon32.png",
      "48": "icons/icon48.png",
      "128": "icons/icon128.png"
    }
  },
  "icons": {
    "16": "icons/icon16.png",
    "32": "icons/icon32.png",
    "48": "icons/icon48.png",
    "128": "icons/icon128.png"
  },
  "browser_specific_settings": {
    "gecko": {
      "id": "{8f7c9d2a-4b3e-4c1d-9a2f-5e6b7c8d9e0f}",
      "strict_min_version": "109.0"
    }
  },
  "content_security_policy": {
    "extension_pages": "script-src 'self'; object-src 'self'"
  }
}
